<pkg-contents spec="1.12"><f n="gdbm" o="root" g="staff" p="16877" pt="/Users/ranger/rcs/kde/kde-mac/gdbm/destdir/gdbm" m="false" t="file"><f n="include" o="ranger" g="staff" p="16893"><f n="gdbm.h" o="ranger" g="staff" p="33204"><mod>mode</mod></f><mod>mode</mod></f><f n="info" o="ranger" g="staff" p="16893"><mod>mode</mod></f><f n="lib" o="root" g="admin" p="16877"><f n="libgdbm.3.dylib" o="root" g="admin" p="33277"><mod>mode</mod></f><f n="libgdbm.dylib" o="root" g="admin" p="33277"><mod>mode</mod></f><f n="libgdbm.la" o="root" g="admin" p="33277"><mod>mode</mod></f></f><f n="man" o="ranger" g="staff" p="16893"><f n="man3" o="ranger" g="staff" p="16893"><mod>mode</mod></f><mod>mode</mod></f><f n="share" o="ranger" g="staff" p="16893"><f n="info" o="ranger" g="staff" p="16893"><f n="gdbm.info" o="ranger" g="staff" p="33204"><mod>mode</mod></f><mod>mode</mod></f><f n="man" o="ranger" g="staff" p="16893"><f n="man3" o="ranger" g="staff" p="16893"><f n="gdbm.3" o="ranger" g="staff" p="33204"><mod>mode</mod></f><mod>mode</mod></f><mod>mode</mod></f><mod>mode</mod></f></f></pkg-contents>